MANIFEST.in
README.md
VERSION
setup.py
libsignetsim/LibSigNetSimException.py
libsignetsim/__init__.py
libsignetsim/__main__.py
libsignetsim.egg-info/PKG-INFO
libsignetsim.egg-info/SOURCES.txt
libsignetsim.egg-info/dependency_links.txt
libsignetsim.egg-info/requires.txt
libsignetsim.egg-info/top_level.txt
libsignetsim/combine/CombineArchive.py
libsignetsim/combine/CombineException.py
libsignetsim/combine/File.py
libsignetsim/combine/ListOfFiles.py
libsignetsim/combine/Manifest.py
libsignetsim/combine/__init__.py
libsignetsim/combine/tests/TestCreateArchive.py
libsignetsim/combine/tests/TestNoManifest.py
libsignetsim/combine/tests/TestOneStep.py
libsignetsim/combine/tests/TestParameterScan1D.py
libsignetsim/combine/tests/TestRunSedmls.py
libsignetsim/combine/tests/TestShowCase.py
libsignetsim/combine/tests/__init__.py
libsignetsim/combine/tests/files/00001-sbml-l3v1-sedml.xml
libsignetsim/combine/tests/files/00001-sbml-l3v1.xml
libsignetsim/combine/tests/files/00001.omex
libsignetsim/combine/tests/files/BIOMD0000000003.sedx
libsignetsim/combine/tests/files/CombineArchiveShowCase.omex
libsignetsim/combine/tests/files/experiment_0.xml
libsignetsim/combine/tests/files/oneStep.sedx
libsignetsim/combine/tests/files/parameterScan1D.sedx
libsignetsim/combine/tests/files/parameterScan2D.sedx
libsignetsim/continuation/EquilibriumPointCurve.py
libsignetsim/continuation/PyDSToolModel.py
libsignetsim/continuation/__init__.py
libsignetsim/continuation/tests/TestContinuation.py
libsignetsim/continuation/tests/TestContinuationDas.py
libsignetsim/continuation/tests/__init__.py
libsignetsim/continuation/tests/files/ras_das.xml
libsignetsim/continuation/tests/files/ras_das_full.xml
libsignetsim/continuation/tests/files/tyson2.xml
libsignetsim/cwriter/CMathWriter.py
libsignetsim/cwriter/CModelWriter.py
libsignetsim/cwriter/CWriterData.py
libsignetsim/cwriter/CWriterModelVsDataOptimization.py
libsignetsim/cwriter/CWriterModels.py
libsignetsim/cwriter/CWriterOptimization.py
libsignetsim/cwriter/__init__.py
libsignetsim/data/Experiment.py
libsignetsim/data/ExperimentalCondition.py
libsignetsim/data/ExperimentalData.py
libsignetsim/data/ListOfExperimentalData.py
