Metadata-Version: 1.0
Name: libsignetsim
Version: 1.0.0a5
Summary: A library designed for building, adjusting and analyzing quantitative biological models. 
Home-page: UNKNOWN
Author: Vincent Noel
Author-email: contact@vincent-noel.fr
License: UNKNOWN
Platform: UNKNOWN
